[
  {
    "date": "2026-03-13",
    "amount": 150,
    "description": "Test Grocery Purchase",
    "merchant": null,
    "category_id": null,
    "payment_method": null,
    "is_income": false,
    "income_source_id": null,
    "is_recurring": false,
    "recurrence_id": null,
    "notes": null,
    "receipt_note": null,
    "id": 4,
    "created_at": "2026-03-13T01:49:26.118141",
    "updated_at": "2026-03-13T01:49:26.118147"
  },
  {
    "date": "2026-03-12",
    "amount": 120,
    "description": "Electric Bill",
    "merchant": null,
    "category_id": null,
    "payment_method": null,
    "is_income": false,
    "income_source_id": null,
    "is_recurring": true,
    "recurrence_id": 5,
    "notes": null,
    "receipt_note": null,
    "id": 16,
    "created_at": "2026-03-13T03:22:11.005945",
    "updated_at": "2026-03-13T03:22:11.005948"
  },
  {
    "date": "2026-03-12",
    "amount": 80,
    "description": "Internet Service",
    "merchant": null,
    "category_id": null,
    "payment_method": null,
    "is_income": false,
    "income_source_id": null,
    "is_recurring": true,
    "recurrence_id": 6,
    "notes": null,
    "receipt_note": null,
    "id": 15,
    "created_at": "2026-03-13T02:50:25.706379",
    "updated_at": "2026-03-13T02:50:25.706381"
  },
  {
    "date": "2026-03-12",
    "amount": 100,
    "description": "Bill payment: electric",
    "merchant": null,
    "category_id": null,
    "payment_method": null,
    "is_income": false,
    "income_source_id": null,
    "is_recurring": false,
    "recurrence_id": null,
    "notes": "Auto-created from V1 bill mark-paid (item #6)",
    "receipt_note": null,
    "id": 3,
    "created_at": "2026-03-12T23:04:51.889214",
    "updated_at": "2026-03-12T23:04:51.889216"
  },
  {
    "date": "2026-03-12",
    "amount": 75,
    "description": "V2 Water Bill",
    "merchant": null,
    "category_id": null,
    "payment_method": null,
    "is_income": false,
    "income_source_id": null,
    "is_recurring": true,
    "recurrence_id": 1,
    "notes": null,
    "receipt_note": null,
    "id": 2,
    "created_at": "2026-03-12T19:53:28.000487",
    "updated_at": "2026-03-12T19:53:28.000490"
  },
  {
    "date": "2026-03-12",
    "amount": 75,
    "description": "Bill payment: Mark Paid Test Bill",
    "merchant": null,
    "category_id": null,
    "payment_method": null,
    "is_income": false,
    "income_source_id": null,
    "is_recurring": false,
    "recurrence_id": null,
    "notes": "Auto-created from V1 bill mark-paid (item #5)",
    "receipt_note": null,
    "id": 1,
    "created_at": "2026-03-12T19:46:24.925893",
    "updated_at": "2026-03-12T19:46:24.925895"
  },
  {
    "date": "2026-03-10",
    "amount": 1200,
    "description": "Freelance Payment",
    "merchant": null,
    "category_id": null,
    "payment_method": "Wire Transfer",
    "is_income": true,
    "income_source_id": 3,
    "is_recurring": false,
    "recurrence_id": null,
    "notes": null,
    "receipt_note": null,
    "id": 14,
    "created_at": "2026-03-13T02:27:28.945660",
    "updated_at": "2026-03-13T02:27:28.945665"
  },
  {
    "date": "2026-03-10",
    "amount": 18.75,
    "description": "Lunch takeout",
    "merchant": "Chipotle",
    "category_id": 7,
    "payment_method": "Debit Card",
    "is_income": false,
    "income_source_id": null,
    "is_recurring": false,
    "recurrence_id": null,
    "notes": null,
    "receipt_note": null,
    "id": 8,
    "created_at": "2026-03-13T02:27:28.753415",
    "updated_at": "2026-03-13T02:27:28.753421"
  },
  {
    "date": "2026-03-09",
    "amount": 62.18,
    "description": "Grocery Run",
    "merchant": "Trader Joes",
    "category_id": 2,
    "payment_method": "Credit Card",
    "is_income": false,
    "income_source_id": null,
    "is_recurring": false,
    "recurrence_id": null,
    "notes": null,
    "receipt_note": null,
    "id": 6,
    "created_at": "2026-03-13T02:27:28.681819",
    "updated_at": "2026-03-13T02:27:28.681823"
  },
  {
    "date": "2026-03-08",
    "amount": 34.99,
    "description": "Concert tickets",
    "merchant": "Ticketmaster",
    "category_id": 8,
    "payment_method": "Credit Card",
    "is_income": false,
    "income_source_id": null,
    "is_recurring": false,
    "recurrence_id": null,
    "notes": null,
    "receipt_note": null,
    "id": 10,
    "created_at": "2026-03-13T02:27:28.819171",
    "updated_at": "2026-03-13T02:27:28.819177"
  },
  {
    "date": "2026-03-07",
    "amount": 45.3,
    "description": "Dinner with friends",
    "merchant": "Olive Garden",
    "category_id": 7,
    "payment_method": "Credit Card",
    "is_income": false,
    "income_source_id": null,
    "is_recurring": false,
    "recurrence_id": null,
    "notes": null,
    "receipt_note": null,
    "id": 7,
    "created_at": "2026-03-13T02:27:28.718557",
    "updated_at": "2026-03-13T02:27:28.718564"
  },
  {
    "date": "2026-03-06",
    "amount": 52.4,
    "description": "Gas fill-up",
    "merchant": "Shell Station",
    "category_id": 4,
    "payment_method": "Debit Card",
    "is_income": false,
    "income_source_id": null,
    "is_recurring": false,
    "recurrence_id": null,
    "notes": null,
    "receipt_note": null,
    "id": 9,
    "created_at": "2026-03-13T02:27:28.787797",
    "updated_at": "2026-03-13T02:27:28.787802"
  },
  {
    "date": "2026-03-05",
    "amount": 87.42,
    "description": "Weekly Groceries",
    "merchant": "Whole Foods",
    "category_id": 2,
    "payment_method": "Debit Card",
    "is_income": false,
    "income_source_id": null,
    "is_recurring": false,
    "recurrence_id": null,
    "notes": null,
    "receipt_note": null,
    "id": 5,
    "created_at": "2026-03-13T02:27:28.641970",
    "updated_at": "2026-03-13T02:27:28.641974"
  },
  {
    "date": "2026-03-04",
    "amount": 42.15,
    "description": "Haircut & styling",
    "merchant": "Great Clips",
    "category_id": 11,
    "payment_method": "Cash",
    "is_income": false,
    "income_source_id": null,
    "is_recurring": false,
    "recurrence_id": null,
    "notes": null,
    "receipt_note": null,
    "id": 11,
    "created_at": "2026-03-13T02:27:28.849295",
    "updated_at": "2026-03-13T02:27:28.849301"
  },
  {
    "date": "2026-03-03",
    "amount": 40,
    "description": "New headphones",
    "merchant": "Amazon",
    "category_id": 9,
    "payment_method": "Credit Card",
    "is_income": false,
    "income_source_id": null,
    "is_recurring": false,
    "recurrence_id": null,
    "notes": null,
    "receipt_note": null,
    "id": 12,
    "created_at": "2026-03-13T02:27:28.883916",
    "updated_at": "2026-03-13T02:27:28.883923"
  },
  {
    "date": "2026-03-01",
    "amount": 5000,
    "description": "March Salary",
    "merchant": null,
    "category_id": null,
    "payment_method": "Direct Deposit",
    "is_income": true,
    "income_source_id": 2,
    "is_recurring": false,
    "recurrence_id": null,
    "notes": null,
    "receipt_note": null,
    "id": 13,
    "created_at": "2026-03-13T02:27:28.914942",
    "updated_at": "2026-03-13T02:27:28.914949"
  }
]